{
    "1": {
        "method": "createTable",
        "params": [
            {
                "name": "discord_sync_posts",
                "columns": {
                    "id": {
                        "name": "id",
                        "type": "BIGINT",
                        "length": "20",
                        "unsigned": true,
                        "zerofill": false,
                        "binary": false,
                        "allow_null": false,
                        "default": null,
                        "auto_increment": true,
                        "comment": "ID Number"
                    },
                    "post_id": {
                        "name": "post_id",
                        "type": "INT",
                        "length": 10,
                        "decimals": null,
                        "values": null,
                        "allow_null": false,
                        "default": null,
                        "comment": "Post id to be synced",
                        "unsigned": true,
                        "zerofill": false,
                        "auto_increment": false,
                        "binary": false
                    },
                    "discord_channel_ids": {
                        "name": "discord_channel_ids",
                        "type": "TEXT",
                        "length": null,
                        "decimals": null,
                        "values": null,
                        "allow_null": false,
                        "default": null,
                        "comment": "The discord channel ids to which the notification should be sent.",
                        "unsigned": false,
                        "zerofill": false,
                        "auto_increment": false,
                        "binary": false
                    }
                },
                "indexes": {
                    "PRIMARY": {
                        "type": "primary",
                        "name": "PRIMARY",
                        "columns": [
                            "id"
                        ],
                        "length": [
                            null
                        ]
                    }
                }
            }
        ]
    },
    "2": {
        "method": "createTable",
        "params": [
            {
                "name": "discord_sync_groups",
                "columns": {
                    "id": {
                        "name": "id",
                        "type": "BIGINT",
                        "length": "20",
                        "unsigned": true,
                        "zerofill": false,
                        "binary": false,
                        "allow_null": false,
                        "default": null,
                        "auto_increment": true,
                        "comment": "ID Number"
                    },
                    "member_id": {
                        "name": "member_id",
                        "type": "BIGINT",
                        "length": 20,
                        "decimals": null,
                        "values": null,
                        "allow_null": true,
                        "default": null,
                        "comment": "Members which need to be synchronized",
                        "unsigned": true,
                        "zerofill": false,
                        "auto_increment": false,
                        "binary": false
                    }
                },
                "indexes": {
                    "PRIMARY": {
                        "type": "primary",
                        "name": "PRIMARY",
                        "columns": [
                            "id"
                        ],
                        "length": [
                            null
                        ]
                    }
                }
            }
        ]
    },
    "3": {
        "method": "createTable",
        "params": [
            {
                "name": "discord_sync_calendar_events",
                "columns": {
                    "id": {
                        "name": "id",
                        "type": "BIGINT",
                        "length": "20",
                        "unsigned": true,
                        "zerofill": false,
                        "binary": false,
                        "allow_null": false,
                        "default": null,
                        "auto_increment": true,
                        "comment": "ID Number"
                    },
                    "calendar_event_id": {
                        "name": "calendar_event_id",
                        "type": "INT",
                        "length": 10,
                        "decimals": null,
                        "values": null,
                        "allow_null": false,
                        "default": null,
                        "comment": "The calendar event id to sync",
                        "unsigned": true,
                        "zerofill": false,
                        "auto_increment": false,
                        "binary": false
                    },
                    "discord_channel_id": {
                        "name": "discord_channel_id",
                        "type": "VARCHAR",
                        "length": 20,
                        "decimals": null,
                        "values": null,
                        "allow_null": false,
                        "default": "",
                        "comment": "The discord channel id to post this event to",
                        "unsigned": false,
                        "zerofill": false,
                        "auto_increment": false,
                        "binary": false
                    }
                },
                "indexes": {
                    "PRIMARY": {
                        "type": "primary",
                        "name": "PRIMARY",
                        "columns": [
                            "id"
                        ],
                        "length": [
                            null
                        ]
                    }
                }
            }
        ]
    },
    "4": {
        "method": "createTable",
        "params": [
            {
                "name": "discord_sync_downloads_files",
                "columns": {
                    "id": {
                        "name": "id",
                        "type": "BIGINT",
                        "length": "20",
                        "unsigned": true,
                        "zerofill": false,
                        "binary": false,
                        "allow_null": false,
                        "default": null,
                        "auto_increment": true,
                        "comment": "ID Number"
                    },
                    "downloads_file_id": {
                        "name": "downloads_file_id",
                        "type": "INT",
                        "length": 10,
                        "decimals": null,
                        "values": null,
                        "allow_null": false,
                        "default": null,
                        "comment": "The file id to sync",
                        "unsigned": true,
                        "zerofill": false,
                        "auto_increment": false,
                        "binary": false
                    },
                    "discord_channel_id": {
                        "name": "discord_channel_id",
                        "type": "VARCHAR",
                        "length": 20,
                        "decimals": null,
                        "values": null,
                        "allow_null": false,
                        "default": null,
                        "comment": "The discord channel id to post to",
                        "unsigned": false,
                        "zerofill": false,
                        "auto_increment": false,
                        "binary": false
                    }
                },
                "indexes": {
                    "PRIMARY": {
                        "type": "primary",
                        "name": "PRIMARY",
                        "columns": [
                            "id"
                        ],
                        "length": [
                            null
                        ]
                    }
                }
            }
        ]
    },
    "5": {
        "method": "createTable",
        "params": [
            {
                "name": "discord_sync_topics",
                "columns": {
                    "id": {
                        "name": "id",
                        "type": "BIGINT",
                        "length": "20",
                        "unsigned": true,
                        "zerofill": false,
                        "binary": false,
                        "allow_null": false,
                        "default": null,
                        "auto_increment": true,
                        "comment": "ID Number"
                    },
                    "topic_id": {
                        "name": "topic_id",
                        "type": "INT",
                        "length": 10,
                        "decimals": null,
                        "values": null,
                        "allow_null": false,
                        "default": null,
                        "comment": "The topic id to sync",
                        "unsigned": true,
                        "zerofill": false,
                        "auto_increment": false,
                        "binary": false
                    },
                    "discord_channel_id": {
                        "name": "discord_channel_id",
                        "type": "VARCHAR",
                        "length": 20,
                        "decimals": null,
                        "values": null,
                        "allow_null": false,
                        "default": null,
                        "comment": "The channel id to sync to",
                        "unsigned": false,
                        "zerofill": false,
                        "auto_increment": false,
                        "binary": false
                    }
                },
                "indexes": {
                    "PRIMARY": {
                        "type": "primary",
                        "name": "PRIMARY",
                        "columns": [
                            "id"
                        ],
                        "length": [
                            null
                        ]
                    }
                }
            }
        ]
    }
}